deeproc/ConcordanceMatrixPlot.py
deeproc/DeepROC.py
deeproc/FullROC.py
deeproc/SimpleROC.py
deeproc/TestDeepROC.py
deeproc/TestVectors.py
deeproc/__init__.py
deeproc/Helpers/DeepROCFunctions.py
deeproc/Helpers/DeepROCInterpolation.py
deeproc/Helpers/DeepROCPlot.py
deeproc/Helpers/FullROCPlot.py
deeproc/Helpers/ROCFunctions.py
deeproc/Helpers/ROCPlot.py
deeproc/Helpers/__init__.py
deeproc/Helpers/transcript.py
deeproc-1.0.17.dist-info/METADATA
deeproc-1.0.17.dist-info/WHEEL
deeproc-1.0.17.dist-info/top_level.txt
deeproc-1.0.17.dist-info/RECORD
