Metadata-Version: 2.1
Name: deeproc
Version: 1.0.17
Summary: Deep ROC analysis toolkit
Home-page: https://github.com/Big-Life-Lab/deepROC
Author: Andre Carrington
Author-email: amcarrin@gmail.com
Project-URL: Bug Tracker, https://github.com/Big-Life-Lab/deepROC/issues
Classifier: Programming Language :: Python :: 3
Classifier: License :: OSI Approved :: Apache Software License
Classifier: Operating System :: OS Independent
Requires-Python: >=3.6
